contest_builder/__init__.py
contest_builder/cli.py
contest_builder/actions/problem_actions.py
contest_builder/configs/main.json
contest_builder/executors/cpp_executor.py
contest_builder/executors/executor.py
contest_builder/executors/general_executor.py
contest_builder/executors/program_excecutor.py
contest_builder/executors/python_executor.py
contest_builder/generators/contest_generator.py
contest_builder/generators/problem_generator.py
contest_builder/helpers/command/command_helper.py
contest_builder/helpers/config/config.py
contest_builder/helpers/config/local_config.py
contest_builder/helpers/config/templates.py
contest_builder/helpers/file/file_helper.py
contest_builder/helpers/folder/folder_helper.py
contest_builder/helpers/model/language_helper.py
contest_builder/helpers/model/model_helper.py
contest_builder/helpers/model/problem_helper.py
contest_builder/helpers/model/finders/language_finder.py
contest_builder/helpers/model/finders/provider_finder.py
contest_builder/helpers/terminal/arg_helper.py
contest_builder/helpers/terminal/cat_helper.py
contest_builder/helpers/terminal/single_process.py
contest_builder/helpers/type/platform_helper.py
contest_builder/helpers/utils/timer.py
contest_builder/mediators/base_mediator.py
contest_builder/mediators/contest_mediator.py
contest_builder/mediators/execution_mediator.py
contest_builder/mediators/init_mediator.py
contest_builder/mediators/problem_mediator.py
contest_builder/models/contest.py
contest_builder/models/language.py
contest_builder/models/problem.py
contest_builder/models/provider.py
contest_builder/templates/template.json
contest_builder/templates/codeforces/template.cpp
contest_builder/templates/codeforces/template.py
contest_builder/templates/leetcode/template.cpp
contest_builder/templates/leetcode/template.py
contest_builder/types/languages.py
contest_builder/types/name_types.py
contest_builder/types/platforms.py
contest_builder/types/providers.py
contest_builder-0.0.14.dist-info/licenses/LICENSE
contest_builder-0.0.14.dist-info/METADATA
contest_builder-0.0.14.dist-info/WHEEL
contest_builder-0.0.14.dist-info/entry_points.txt
contest_builder-0.0.14.dist-info/top_level.txt
contest_builder-0.0.14.dist-info/RECORD
