Metadata-Version: 2.4
Name: contest-builder
Version: 0.0.14
Summary: Competetive Programming Management Tool
Author-email: shamir0xe <shamir0xe@gmail.com>
License: MIT License
Project-URL: Homepage, https://github.com/shamir0xe/contest-builder
Keywords: competetive,programming,CP,manager,compile tool,codeforces
Classifier: License :: OSI Approved :: MIT License
Classifier: Programming Language :: Python
Classifier: Programming Language :: Python :: 3
Classifier: Operating System :: OS Independent
Requires-Python: >=3.12.3
License-File: LICENSE
Requires-Dist: pylib-0xe==0.1.3
Provides-Extra: dev
Requires-Dist: pytest; extra == "dev"
Requires-Dist: pyfakefs; extra == "dev"
Requires-Dist: pytest-mock; extra == "dev"
Dynamic: license-file
